aws_cdk/aws_cognito/__init__.py
aws_cdk/aws_cognito/py.typed
aws_cdk/aws_cognito/_jsii/__init__.py
aws_cdk/aws_cognito/_jsii/aws-cognito@1.204.0.jsii.tgz
aws_cdk.aws_cognito-1.204.0.dist-info/LICENSE
aws_cdk.aws_cognito-1.204.0.dist-info/METADATA
aws_cdk.aws_cognito-1.204.0.dist-info/NOTICE
aws_cdk.aws_cognito-1.204.0.dist-info/WHEEL
aws_cdk.aws_cognito-1.204.0.dist-info/top_level.txt
aws_cdk.aws_cognito-1.204.0.dist-info/RECORD
